[
    {
        "name": "Contabilidade",
        "type": "accounting"
    },
    {
        "name": "Aeroporto",
        "type": "airport"
    },
    {
        "name": "Parque de diversões",
        "type": "amusement_park"
    },
    {
        "name": "Aquário",
        "type": "aquarium"
    },
    {
        "name": "Galeria de Arte",
        "type": "art_gallery"
    },
    {
        "name": "Caixa Eletrônico",
        "type": "atm"
    },
    {
        "name": "Padaria",
        "type": "bakery"
    },
    {
        "name": "Banco",
        "type": "bank"
    },
    {
        "name": "Bar",
        "type": "bar"
    },
    {
        "name": "Salão de beleza",
        "type": "beauty_salon"
    },
    {
        "name": "Loja de Bicicleta",
        "type": "bicycle_store"
    },
    {
        "name": "Livraria",
        "type": "book_store"
    },
    {
        "name": "Bowling",
        "type": "bowling_alley"
    },
    {
        "name": "Estação de onibus",
        "type": "bus_station"
    },
    {
        "name": "Café",
        "type": "cafe"
    },
    {
        "name": "Área de camping",
        "type": "campground"
    },
    {
        "name": "Vendedor de carros",
        "type": "car_dealer"
    },
    {
        "name": "Alugeul de Carro",
        "type": "car_rental"
    },
    {
        "name": "Reparo do carro",
        "type": "car_repair"
    },
    {
        "name": "Lava-jato",
        "type": "car_wash"
    },
    {
        "name": "Cassino",
        "type": "casino"
    },
    {
        "name": "Cemitério",
        "type": "cemetery"
    },
    {
        "name": "Igreja",
        "type": "church"
    },
    {
        "name": "Prefeitura",
        "type": "city_hall"
    },
    {
        "name": "Loja de roupas",
        "type": "clothing_store"
    },
    {
        "name": "Loja de conveniência",
        "type": "convenience_store"
    },
    {
        "name": "Tribunal",
        "type": "courthouse"
    },
    {
        "name": "Dentista",
        "type": "dentist"
    },
    {
        "name": "Loja de departamento",
        "type": "department_store"
    },
    {
        "name": "Médico",
        "type": "doctor"
    },
    {
        "name": "Eletricista",
        "type": "electrician"
    },
    {
        "name": "Loja de eletrônicos",
        "type": "electronics_store"
    },
    {
        "name": "Embaixada",
        "type": "embassy"
    },
    {
        "name": "Corpo de Bombeiros",
        "type": "fire_station"
    },
    {
        "name": "Florista",
        "type": "florist"
    },
    {
        "name": "Funerária",
        "type": "funeral_home"
    },
    {
        "name": "Loja de móveis",
        "type": "furniture_store"
    },
    {
        "name": "Posto de gasolina",
        "type": "gas_station"
    },
    {
        "name": "Academia",
        "type": "gym"
    },
    {
        "name": "Cuidado capilar",
        "type": "hair_care"
    },
    {
        "name": "Loja de Hardware",
        "type": "hardware_store"
    },
    {
        "name": "hindu_temple",
        "type": "hindu_temple"
    },
    {
        "name": "home_goods_store",
        "type": "home_goods_store"
    },
    {
        "name": "hospital",
        "type": "hospital"
    },
    {
        "name": "Agência de seguros",
        "type": "insurance_agency"
    },
    {
        "name": "jewelry_store",
        "type": "jewelry_store"
    },
    {
        "name": "Lavanderia",
        "type": "laundry"
    },
    {
        "name": "Advogado",
        "type": "lawyer"
    },
    {
        "name": "Biblioteca",
        "type": "library"
    },
    {
        "name": "Liquor_store",
        "type": "liquor_store"
    },
    {
        "name": "Local_government_office",
        "type": "local_government_office"
    },
    {
        "name": "Chaveiro",
        "type": "locksmith"
    },
    {
        "name": "Alojamento",
        "type": "lodging"
    },
    {
        "name": "meal_delivery",
        "type": "meal_delivery"
    },
    {
        "name": "meal_takeaway",
        "type": "meal_takeaway"
    },
    {
        "name": "Mesquita",
        "type": "mosque"
    },
    {
        "name": "movie_rental",
        "type": "movie_rental"
    },
    {
        "name": "Cinema",
        "type": "movie_theater"
    },
    {
        "name": "moving_company",
        "type": "moving_company"
    },
    {
        "name": "Museu",
        "type": "museum"
    },
    {
        "name": "Boate",
        "type": "night_club"
    },
    {
        "name": "Pintor",
        "type": "painter"
    },
    {
        "name": "Parque",
        "type": "park"
    },
    {
        "name": "Estacionamento",
        "type": "parking"
    },
    {
        "name": "Loja de animais",
        "type": "pet_store"
    },
    {
        "name": "Farmacia",
        "type": "pharmacy"
    },
    {
        "name": "Fisioterapeuta",
        "type": "physiotherapist"
    },
    {
        "name": "Encanador",
        "type": "plumber"
    },
    {
        "name": "Polícia",
        "type": "police"
    },
    {
        "name": "Agência dos Correios",
        "type": "post_office"
    },
    {
        "name": "Agência imobiliária",
        "type": "real_estate_agency"
    },
    {
        "name": "Restaurante",
        "type": "restaurant"
    },
    {
        "name": "roofing_contractor",
        "type": "roofing_contractor"
    },
    {
        "name": "rv_park",
        "type": "rv_park"
    },
    {
        "name": "Escola",
        "type": "school"
    },
    {
        "name": "Loja de sapatos",
        "type": "shoe_store"
    },
    {
        "name": "Centro de compras",
        "type": "shopping_mall"
    },
    {
        "name": "Estádio",
        "type": "stadium"
    },
    {
        "name": "Armazenamento",
        "type": "storage"
    },
    {
        "name": "Loja",
        "type": "store"
    },
    {
        "name": "Estação de metrô",
        "type": "subway_station"
    },
    {
        "name": "Supermercado",
        "type": "supermarket"
    },
    {
        "name": "Sinagoga",
        "type": "synagogue"
    },
    {
        "name": "Ponto de taxi",
        "type": "taxi_stand"
    },
    {
        "name": "Estação de trem",
        "type": "train_station"
    },
    {
        "name": "Estação de trânsito",
        "type": "transit_station"
    },
    {
        "name": "Agência de viagens",
        "type": "travel_agency"
    },
    {
        "name": "Cuidados veterinários",
        "type": "veterinary_care"
    },
    {
        "name": "Zoológico",
        "type": "zoo"
    }
]